samudra_scale/__init__.py
samudra_scale/decoder.py
samudra_scale-0.1.2.dist-info/LICENSE
samudra_scale-0.1.2.dist-info/METADATA
samudra_scale-0.1.2.dist-info/WHEEL
samudra_scale-0.1.2.dist-info/top_level.txt
samudra_scale-0.1.2.dist-info/RECORD
