Metadata-Version: 2.1
Name: samudra_scale
Version: 0.1.2
Summary: A python library for extracting weights from byte data
Home-page: https://github.com/dap23/samudra-scale
Author: Muhammad Daffa
Author-email: mdaffa2301@gmail.com
Classifier: Programming Language :: Python :: 3
Classifier: License :: OSI Approved :: MIT License
Classifier: Operating System :: OS Independent
Requires-Python: >=3.6
License-File: LICENSE
